vdit/__init__.py
vdit/__main__.py
vdit-0.2.0.dist-info/METADATA
vdit-0.2.0.dist-info/WHEEL
vdit-0.2.0.dist-info/entry_points.txt
vdit-0.2.0.dist-info/top_level.txt
vdit-0.2.0.dist-info/RECORD
